{
    "os": "Linux-4.4.0-201-generic-x86_64-with-debian-stretch-sid",
    "python": "3.6.12",
    "heartbeatAt": "2021-02-06T14:56:05.996912",
    "startedAt": "2021-02-06T14:56:03.624404",
    "docker": null,
    "gpu": "TITAN Xp",
    "gpu_count": 10,
    "cpu_count": 56,
    "cuda": "10.0.130",
    "args": [
        "--exp_name",
        "hybrid-agent-1",
        "--batch_size",
        "32",
        "--img_feat_input_dim",
        "2048",
        "--img_fc_dim",
        "1024",
        "--rnn_hidden_size",
        "512",
        "--eval_every_epoch",
        "5",
        "--use_ignore_index",
        "1",
        "--arch",
        "hybrid",
        "--model_state",
        "1"
    ],
    "state": "running",
    "codePath": "tasks/R2R/main.py",
    "program": "tasks/R2R/main.py",
    "git": {
        "remote": "https://github.com/awesomericky/Hybrid-VLN.git",
        "commit": "3c4498331ed050429615e79f4bb4d6f215ee6f40"
    },
    "email": "awesomericky@snu.ac.kr",
    "root": "/disk2/yunhokim/Hybrid-VLN",
    "host": "mewtwo",
    "username": "intern",
    "executable": "/home/intern/miniconda3/envs/r2r_v2/bin/python"
}
